abusers/__init__.py
abusers/camegame.py
data_lab/camegame.py
camegame-0.0.61.dist-info/METADATA
camegame-0.0.61.dist-info/WHEEL
camegame-0.0.61.dist-info/top_level.txt
camegame-0.0.61.dist-info/RECORD
